minerva/__init__.py
minerva/_version.py
minerva/async_helper.py
minerva/config.py
minerva/database.py
minerva/dataset.py
minerva/index.py
minerva/tasks.py
minerva/controllers/__init__.py
minerva/controllers/dataset.py
minerva/controllers/generator.py
minerva/controllers/project.py
minerva/controllers/system.py
minerva/dist/favicon.ico
minerva/dist/index.bundle.js
minerva/dist/index.html
minerva/models/__init__.py
minerva/models/base.py
minerva/models/dataset.py
minerva/models/experiment.py
minerva/models/project.py
minerva_ui-0.40.dist-info/LICENSE
minerva_ui-0.40.dist-info/METADATA
minerva_ui-0.40.dist-info/WHEEL
minerva_ui-0.40.dist-info/entry_points.txt
minerva_ui-0.40.dist-info/top_level.txt
minerva_ui-0.40.dist-info/RECORD
