Metadata-Version: 2.1
Name: minerva-ui
Version: 0.40
Summary: An out-of-the-box GUI tool for offline deep reinforcement learning
Home-page: https://github.com/takuseno/minerva
Author: Takuma Seno
Author-email: takuma.seno@gmail.com
License: MIT License
Platform: UNKNOWN
Classifier: Development Status :: 4 - Beta
Classifier: Intended Audience :: Developers
Classifier: Intended Audience :: Education
Classifier: Intended Audience :: Science/Research
Classifier: Topic :: Scientific/Engineering
Classifier: Topic :: Scientific/Engineering :: Artificial Intelligence
Classifier: Programming Language :: Python :: 3.6
Classifier: Programming Language :: Python :: 3.7
Classifier: Programming Language :: Python :: 3.8
Classifier: Programming Language :: Python :: Implementation :: CPython
Classifier: Operating System :: POSIX :: Linux
Classifier: Operating System :: MacOS :: MacOS X
Requires-Python: >=3.5.0
Requires-Dist: d3rlpy (==0.90)
Requires-Dist: Flask
Requires-Dist: flask-sqlalchemy
Requires-Dist: flask-marshmallow
Requires-Dist: Flask-Migrate
Requires-Dist: SQLAlchemy
Requires-Dist: marshmallow-sqlalchemy
Requires-Dist: click
Requires-Dist: Pillow
